funcopy/__init__.py
funcopy/setup.py
funcopy-0.2.0.dist-info/METADATA
funcopy-0.2.0.dist-info/WHEEL
funcopy-0.2.0.dist-info/top_level.txt
funcopy-0.2.0.dist-info/RECORD
