Metadata-Version: 2.1
Name: funcopy
Version: 0.2.0
Summary: funcopy: copy a func
Home-page: UNKNOWN
Author: TvoozMagnificent
Author-email: luchang1106@icloud.com
License: MIT
Platform: UNKNOWN
Classifier: License :: OSI Approved :: MIT License
Classifier: Programming Language :: Python :: 3
